setup.py
phoenix_ml3/NN.py
phoenix_ml3/__init__.py
phoenix_ml3/back_prop.py
phoenix_ml3/cnn.py
phoenix_ml3/data_loader.py
phoenix_ml3/data_preprocessing.py
phoenix_ml3/evaluation.py
phoenix_ml3/forward_prop.py
phoenix_ml3/init_param.py
phoenix_ml3/optimization.py
phoenix_ml3/runner.py
phoenix_ml3/utils_module.py
phoenix_ml3/visualization.py
phoenix_ml3.egg-info/PKG-INFO
phoenix_ml3.egg-info/SOURCES.txt
phoenix_ml3.egg-info/dependency_links.txt
phoenix_ml3.egg-info/not-zip-safe
phoenix_ml3.egg-info/top_level.txt